Perceptron/__init__.py
Perceptron/perceptron.py
App_ANN_Project_Praveenku32k-0.0.1.dist-info/LICENSE
App_ANN_Project_Praveenku32k-0.0.1.dist-info/METADATA
App_ANN_Project_Praveenku32k-0.0.1.dist-info/WHEEL
App_ANN_Project_Praveenku32k-0.0.1.dist-info/top_level.txt
App_ANN_Project_Praveenku32k-0.0.1.dist-info/RECORD
