Metadata-Version: 2.1
Name: App-ANN-Project-Praveenku32k
Version: 0.0.1
Summary: its an implimentation of Perceptron
Home-page: https://github.com/Praveenku32k/App_ANN_Project
Author: Praveenku32k
Author-email: praveenku32k@gmail.com
License: UNKNOWN
Project-URL: Bug Tracker, https://github.com/Praveenku32k/App_ANN_Project/issues
Platform: UNKNOWN
Classifier: Programming Language :: Python :: 3
Classifier: License :: OSI Approved :: MIT License
Classifier: Operating System :: OS Independent
Requires-Python: >=3.8
License-File: LICENSE
Requires-Dist: numpy
Requires-Dist: tqdm
